cfractions/__init__.py
cfractions/_cfractions.cpython-311-powerpc64le-linux-gnu.so
cfractions/_fractions.py
cfractions/py.typed
cfractions-2.4.1.dist-info/METADATA
cfractions-2.4.1.dist-info/WHEEL
cfractions-2.4.1.dist-info/top_level.txt
cfractions-2.4.1.dist-info/RECORD
cfractions-2.4.1.dist-info/licenses/LICENSE
