Metadata-Version: 2.4
Name: cfractions
Version: 2.4.1
Summary: Python C API alternative to `fractions` module.
Home-page: https://github.com/lycantropos/cfractions/
Download-URL: https://github.com/lycantropos/cfractions/archive/master.zip
Author-email: Azat Ibrakov <azatibrakov@gmail.com>
License: MIT License
Classifier: License :: OSI Approved :: MIT License
Classifier: Programming Language :: Python :: 3.9
Classifier: Programming Language :: Python :: 3.10
Classifier: Programming Language :: Python :: 3.11
Classifier: Programming Language :: Python :: 3.12
Classifier: Programming Language :: Python :: 3.13
Classifier: Programming Language :: Python :: Implementation :: CPython
Classifier: Programming Language :: Python :: Implementation :: PyPy
Requires-Python: >=3.9
License-File: LICENSE
Requires-Dist: typing-extensions<5.0,>=4.12.2
Provides-Extra: tests
Requires-Dist: hypothesis<7.0,>=6.118.8; extra == "tests"
Requires-Dist: pytest<9.0,>=8.3.3; extra == "tests"
Dynamic: download-url
Dynamic: home-page
Dynamic: license-file
